logservice/__init__.py
logservice/cloudwatch.py
logservice/elk_logger.py
logservice/schema.py
logservice/utils.py
logservice-0.1.7.dist-info/licenses/LICENSE
logservice-0.1.7.dist-info/METADATA
logservice-0.1.7.dist-info/WHEEL
logservice-0.1.7.dist-info/top_level.txt
logservice-0.1.7.dist-info/RECORD
