Metadata-Version: 2.4
Name: logservice
Version: 0.1.7
Summary: Reusable CloudWatch log sender
Author: Naveenkumar Koppala
Author-email: naveenkumar.k@tnsservices.com
License: MIT
Classifier: Programming Language :: Python :: 3
Classifier: Operating System :: OS Independent
Requires-Python: >=3.9
License-File: LICENSE
Requires-Dist: aioboto3>=15.0.0
Requires-Dist: pydantic<3.0.0,>=2.2.7
Dynamic: author
Dynamic: author-email
Dynamic: classifier
Dynamic: description
Dynamic: description-content-type
Dynamic: license
Dynamic: license-file
Dynamic: requires-dist
Dynamic: requires-python
Dynamic: summary
